livekit/plugins/faseeh/__init__.py
livekit/plugins/faseeh/log.py
livekit/plugins/faseeh/models.py
livekit/plugins/faseeh/tts.py
livekit/plugins/faseeh/version.py
livekit_plugins_faseeh-0.1.4.dist-info/METADATA
livekit_plugins_faseeh-0.1.4.dist-info/WHEEL
livekit_plugins_faseeh-0.1.4.dist-info/licenses/LICENSE
livekit_plugins_faseeh-0.1.4.dist-info/RECORD
