Metadata-Version: 2.4
Name: livekit-plugins-faseeh
Version: 0.1.4
Summary: LiveKit Agents plugin for Arabic text-to-speech with Faseeh AI.
Project-URL: Homepage, https://github.com/actualize-ae/livekit-plugins-faseeh
Project-URL: Documentation, https://github.com/actualize-ae/livekit-plugins-faseeh#readme
Project-URL: Repository, https://github.com/actualize-ae/livekit-plugins-faseeh
Project-URL: Bug Tracker, https://github.com/actualize-ae/livekit-plugins-faseeh/issues
Project-URL: Faseeh AI, https://faseeh.ai
Author-email: Khalid Ghiboub <khalid@actualize.ae>
Maintainer-email: Khalid Ghiboub <khalid@actualize.ae>
License-Expression: Apache-2.0
License-File: LICENSE
Keywords: ai,arabic,audio,faseeh,livekit,realtime,speech-synthesis,tts,voice
Classifier: Development Status :: 4 - Beta
Classifier: Intended Audience :: Developers
Classifier: License :: OSI Approved :: Apache Software License
Classifier: Programming Language :: Python :: 3
Classifier: Programming Language :: Python :: 3 :: Only
Classifier: Programming Language :: Python :: 3.9
Classifier: Programming Language :: Python :: 3.10
Classifier: Programming Language :: Python :: 3.11
Classifier: Programming Language :: Python :: 3.12
Classifier: Topic :: Multimedia :: Sound/Audio
Classifier: Topic :: Multimedia :: Video
Classifier: Topic :: Scientific/Engineering :: Artificial Intelligence
Requires-Python: >=3.9.0
Requires-Dist: aiohttp>=3.9.0
Requires-Dist: livekit-agents[codecs]>=1.0.23
